app/client_app.py
venv/bin/rst2html.py
venv/bin/rst2html4.py
venv/bin/rst2html5.py
venv/bin/rst2latex.py
venv/bin/rst2man.py
venv/bin/rst2odt.py
venv/bin/rst2odt_prepstyles.py
venv/bin/rst2pseudoxml.py
venv/bin/rst2s5.py
venv/bin/rst2xetex.py
venv/bin/rst2xml.py
venv/bin/rstpep2html.py
chef_helper-5.dist-info/LICENSE
chef_helper-5.dist-info/METADATA
chef_helper-5.dist-info/WHEEL
chef_helper-5.dist-info/entry_points.txt
chef_helper-5.dist-info/top_level.txt
chef_helper-5.dist-info/RECORD
