Metadata-Version: 2.1
Name: chef-helper
Version: 5
Summary: Helping the chef find meal cooking instructions.
Home-page: http://github.com/osandrey/Chef_helper
Author: OSA
Author-email: osandreyman@gmail.com
License: MIT
License-File: LICENSE
Requires-Dist: requests (==2.29.0)
